dbfsps/__init__.py
dbfsps/cli/__init__.py
dbfsps/cli/databricks_sync.py
dbfsps/cli/utils.py
dbfsps/sdk/__init__.py
dbfsps/sdk/config.py
dbfsps/sdk/dbfs.py
dbfsps/sdk/errors.py
dbfsps/setupnotebook.py
dbfsps/syncer/__init__.py
dbfsps/syncer/file.py
dbfsps/syncer/plan.py
dbfsps/syncer/state.py
dbfs_package_sync-0.2.0.dist-info/METADATA
dbfs_package_sync-0.2.0.dist-info/WHEEL
dbfs_package_sync-0.2.0.dist-info/entry_points.txt
dbfs_package_sync-0.2.0.dist-info/RECORD
