Metadata-Version: 2.1
Name: dbfs-package-sync
Version: 0.2.0
Summary: Basic CLI tool that can sync a local Python package directory with a folder on dbfs
Home-page: https://github.com/jmeidam/dbfs-package-sync
Author: Jeroen Meidam
Author-email: j.meidam@gmail.com
Requires-Python: >=3.9,<4.0
Classifier: Programming Language :: Python :: 3
Classifier: Programming Language :: Python :: 3.9
Classifier: Programming Language :: Python :: 3.10
Classifier: Programming Language :: Python :: 3.11
Requires-Dist: click (>=8.0,<9.0)
Requires-Dist: databricks-cli (>=0.17.7,<0.18.0)
Project-URL: Repository, https://github.com/jmeidam/dbfs-package-sync
